problem_detector/__init__.py
problem_detector/blackboard.py
problem_detector/client.py
problem_detector/problem_detector.py
problem_detector/supervisor.py
problem_detector/collector/__init__.py
problem_detector/collector/status_collector.py
problem_detector/config/policy_config.yaml
problem_detector/config/server_config.yaml
problem_detector/detector/__init__.py
problem_detector/detector/status_detector.py
problem_detector-0.2.0.data/scripts/problem_detector
problem_detector-0.2.0.dist-info/AUTHORS.rst
problem_detector-0.2.0.dist-info/LICENSE
problem_detector-0.2.0.dist-info/METADATA
problem_detector-0.2.0.dist-info/WHEEL
problem_detector-0.2.0.dist-info/top_level.txt
problem_detector-0.2.0.dist-info/RECORD
