Metadata-Version: 2.1
Name: problem-detector
Version: 0.2.0
Summary: Detecting robot's problem and reporting
Home-page: https://bitbucket.org/yujinrobot/problem_detector
Author: SimJoonYeol
Author-email: jysim@yujinrobot.com
License: MIT license
Keywords: problem_detector
Platform: UNKNOWN
Classifier: Development Status :: 2 - Pre-Alpha
Classifier: Intended Audience :: Developers
Classifier: License :: OSI Approved :: MIT License
Classifier: Natural Language :: English
Classifier: Programming Language :: Python :: 3.6
Classifier: Programming Language :: Python :: 3.7
Requires-Dist: requests
Requires-Dist: pyyaml
Requires-Dist: log-aggregator-server (==0.2.1)
